contador/contadorN.v
`timescale 1ms / 100us

module contadorN(
    NEclk,      // Negative-edge clock
    Nreset,     // Not-reset
    Enable,     // Counting Enabler
    count       // Count output
);

parameter BITS = 4; // Parámetro para el tamaño del contador

// Defining I/O
input NEclk, Nreset, Enable;

output [BITS-1 : 0] count;

// Defining Data Types
wire NEclk, Nreset, Enable;

reg [BITS-1 : 0] count;

// Code
always @ (negedge NEclk or Nreset) begin
    if(Nreset == 1'b0) begin
        count <= 0;
    end
    else begin
        if (Enable == 1'b1) begin
            count <= #1 count + 1;
        end else begin
            count <= #1 count;
        end
    end
end

endmodule

contador/clock.v
`timescale 1ms / 100us
module clock_gen(clk);

parameter PERIOD = 2;

output reg clk;
	 
always
	begin: CLOCK_DRIVER
		clk <= 1'b0;
		#(PERIOD/2);
		clk <= 1'b1;
		#(PERIOD/2);
	end
endmodule

contador/contadorN_tb.v
`include "./contadorN.v"
`include "clock.v"
`include "count2watch.v"

`timescale 100us / 100us

module count_tb();

parameter size = 26;

wire clk;
clock_gen #(.PERIOD(10)) clk_gen(clk);
reg nr = 0;
reg enable = 0;
wire [size-1:0] count;
wire [9:0] ms;
wire [5:0] s;
wire [5:0] min;
wire [3:0] hr;

contadorN #(.BITS(size)) counter (
    .NEclk(clk),
    .Nreset(nr),
    .Enable(enable),
    .count(count)
);

initial begin
    #10 nr = 1;
    #10 enable = 1;
    #80 nr = 0;
    #40 nr = 1;
    #20 enable = 0;
    #40 enable = 1;
end

initial begin
    #100000 $finish;
end

initial begin
    $dumpfile("counter_test.vcd");
    $dumpvars;
end

initial begin
    $display("\t\tTime\tcount");
    $monitor("%d\t%d",$time,count);
end

endmodule

contador/count2watch.v
module count2watch(
    count,      // Number of pulses counted
    nreset,     // Resetting the output to 000
    ms,         // Output in ms
    s,          // Output in s
    min,        // Output in min
    hr          // Output in hr
);

parameter BITS = 4;

// Defining I/O
input [BITS-1 : 0] count;
input latch, nreset;

output [10:0] ms;
output [6:0] s;
output [6:0] min;
output [3:0] hr;

// Defining Data Types
wire [BITS-1 : 0] count;
wire latch, nreset;

reg [10:0] ms;
reg [6:0] s;
reg [6:0] min;
reg [3:0] hr;

// Code

always @(*) begin
    ms <= count % 1000;
    s <= (count/1000) % 60;
    min <= (count/1000/60) % 60;
    hr <= (count/1000/60/60) % 10;
end

endmodule

contador/counter_test.vcd
$date
	Mon Nov 19 18:34:26 2018
$end
$version
	Icarus Verilog
$end
$timescale
	100us
$end
$scope module count2watch $end
$var wire 4 ! count [3:0] $end
$var wire 1 " latch $end
$var wire 1 # nreset $end
$var reg 4 $ hr [3:0] $end
$var reg 7 % min [6:0] $end
$var reg 11 & ms [10:0] $end
$var reg 7 ' s [6:0] $end
$upscope $end
$scope module count_tb $end
$var wire 26 ( count [25:0] $end
$var wire 1 ) clk $end
$var reg 1 * enable $end
$var reg 1 + nr $end
$scope module clk_gen $end
$var reg 1 ) clk $end
$scope begin CLOCK_DRIVER $end
$upscope $end
$upscope $end
$scope module counter $end
$var wire 1 * Enable $end
$var wire 1 ) NEclk $end
$var wire 1 + Nreset $end
$var reg 26 , count [25:0] $end
$upscope $end
$upscope $end
$enddefinitions $end
#0
$dumpvars
b0 ,
0+
0*
0)
b0 (
bx '
bx &
bx %
bx $
z#
z"
bz !
$end
#5
1)
#10
0)
1+
#15
1)
#20
0)
1*
#21
b1 (
b1 ,
#25
1)
#30
0)
#31
b10 (
b10 ,
#35
1)
#40
0)
#41
b11 (
b11 ,
#45
1)
#50
0)
#51
b100 (
b100 ,
#55
1)
#60
0)
#61
b101 (
b101 ,
#65
1)
#70
0)
#71
b110 (
b110 ,
#75
1)
#80
0)
#81
b111 (
b111 ,
#85
1)
#90
0)
#91
b1000 (
b1000 ,
#95
1)
#100
b0 (
b0 ,
0)
0+
#105
1)
#110
0)
#115
1)
#120
0)
#125
1)
#130
0)
#135
1)
#140
0)
1+
#141
b1 (
b1 ,
#145
1)
#150
0)
#151
b10 (
b10 ,
#155
1)
#160
0)
0*
#165
1)
#170
0)
#175
1)
#180
0)
#185
1)
#190
0)
#195
1)
#200
0)
1*
#201
b11 (
b11 ,
#205
1)
#210
0)
#211
b100 (
b100 ,
#215
1)
#220
0)
#221
b101 (
b101 ,
#225
1)
#230
0)
#231
b110 (
b110 ,
#235
1)
#240
0)
#241
b111 (
b111 ,
#245
1)
#250
0)
#251
b1000 (
b1000 ,
#255
1)
#260
0)
#261
b1001 (
b1001 ,
#265
1)
#270
0)
#271
b1010 (
b1010 ,
#275
1)
#280
0)
#281
b1011 (
b1011 ,
#285
1)
#290
0)
#291
b1100 (
b1100 ,
#295
1)
#300
0)
#301
b1101 (
b1101 ,
#305
1)
#310
0)
#311
b1110 (
b1110 ,
#315
1)
#320
0)
#321
b1111 (
b1111 ,
#325
1)
#330
0)
#331
b10000 (
b10000 ,
#335
1)
#340
0)
#341
b10001 (
b10001 ,
#345
1)
#350
0)
#351
b10010 (
b10010 ,
#355
1)
#360
0)
#361
b10011 (
b10011 ,
#365
1)
#370
0)
#371
b10100 (
b10100 ,
#375
1)
#380
0)
#381
b10101 (
b10101 ,
#385
1)
#390
0)
#391
b10110 (
b10110 ,
#395
1)
#400
0)
#401
b10111 (
b10111 ,
#405
1)
#410
0)
#411
b11000 (
b11000 ,
#415
1)
#420
0)
#421
b11001 (
b11001 ,
#425
1)
#430
0)
#431
b11010 (
b11010 ,
#435
1)
#440
0)
#441
b11011 (
b11011 ,
#445
1)
#450
0)
#451
b11100 (
b11100 ,
#455
1)
#460
0)
#461
b11101 (
b11101 ,
#465
1)
#470
0)
#471
b11110 (
b11110 ,
#475
1)
#480
0)
#481
b11111 (
b11111 ,
#485
1)
#490
0)
#491
b100000 (
b100000 ,
#495
1)
#500
0)
#501
b100001 (
b100001 ,
#505
1)
#510
0)
#511
b100010 (
b100010 ,
#515
1)
#520
0)
#521
b100011 (
b100011 ,
#525
1)
#530
0)
#531
b100100 (
b100100 ,
#535
1)
#540
0)
#541
b100101 (
b100101 ,
#545
1)
#550
0)
#551
b100110 (
b100110 ,
#555
1)
#560
0)
#561
b100111 (
b100111 ,
#565
1)
#570
0)
#571
b101000 (
b101000 ,
#575
1)
#580
0)
#581
b101001 (
b101001 ,
#585
1)
#590
0)
#591
b101010 (
b101010 ,
#595
1)
#600
0)
#601
b101011 (
b101011 ,
#605
1)
#610
0)
#611
b101100 (
b101100 ,
#615
1)
#620
0)
#621
b101101 (
b101101 ,
#625
1)
#630
0)
#631
b101110 (
b101110 ,
#635
1)
#640
0)
#641
b101111 (
b101111 ,
#645
1)
#650
0)
#651
b110000 (
b110000 ,
#655
1)
#660
0)
#661
b110001 (
b110001 ,
#665
1)
#670
0)
#671
b110010 (
b110010 ,
#675
1)
#680
0)
#681
b110011 (
b110011 ,
#685
1)
#690
0)
#691
b110100 (
b110100 ,
#695
1)
#700
0)
#701
b110101 (
b110101 ,
#705
1)
#710
0)
#711
b110110 (
b110110 ,
#715
1)
#720
0)
#721
b110111 (
b110111 ,
#725
1)
#730
0)
#731
b111000 (
b111000 ,
#735
1)
#740
0)
#741
b111001 (
b111001 ,
#745
1)
#750
0)
#751
b111010 (
b111010 ,
#755
1)
#760
0)
#761
b111011 (
b111011 ,
#765
1)
#770
0)
#771
b111100 (
b111100 ,
#775
1)
#780
0)
#781
b111101 (
b111101 ,
#785
1)
#790
0)
#791
b111110 (
b111110 ,
#795
1)
#800
0)
#801
b111111 (
b111111 ,
#805
1)
#810
0)
#811
b1000000 (
b1000000 ,
#815
1)
#820
0)
#821
b1000001 (
b1000001 ,
#825
1)
#830
0)
#831
b1000010 (
b1000010 ,
#835
1)
#840
0)
#841
b1000011 (
b1000011 ,
#845
1)
#850
0)
#851
b1000100 (
b1000100 ,
#855
1)
#860
0)
#861
b1000101 (
b1000101 ,
#865
1)
#870
0)
#871
b1000110 (
b1000110 ,
#875
1)
#880
0)
#881
b1000111 (
b1000111 ,
#885
1)
#890
0)
#891
b1001000 (
b1001000 ,
#895
1)
#900
0)
#901
b1001001 (
b1001001 ,
#905
1)
#910
0)
#911
b1001010 (
b1001010 ,
#915
1)
#920
0)
#921
b1001011 (
b1001011 ,
#925
1)
#930
0)
#931
b1001100 (
b1001100 ,
#935
1)
#940
0)
#941
b1001101 (
b1001101 ,
#945
1)
#950
0)
#951
b1001110 (
b1001110 ,
#955
1)
#960
0)
#961
b1001111 (
b1001111 ,
#965
1)
#970
0)
#971
b1010000 (
b1010000 ,
#975
1)
#980
0)
#981
b1010001 (
b1010001 ,
#985
1)
#990
0)
#991
b1010010 (
b1010010 ,
#995
1)
#1000
0)
#1001
b1010011 (
b1010011 ,
#1005
1)
#1010
0)
#1011
b1010100 (
b1010100 ,
#1015
1)
#1020
0)
#1021
b1010101 (
b1010101 ,
#1025
1)
#1030
0)
#1031
b1010110 (
b1010110 ,
#1035
1)
#1040
0)
#1041
b1010111 (
b1010111 ,
#1045
1)
#1050
0)
#1051
b1011000 (
b1011000 ,
#1055
1)
#1060
0)
#1061
b1011001 (
b1011001 ,
#1065
1)
#1070
0)
#1071
b1011010 (
b1011010 ,
#1075
1)
#1080
0)
#1081
b1011011 (
b1011011 ,
#1085
1)
#1090
0)
#1091
b1011100 (
b1011100 ,
#1095
1)
#1100
0)
#1101
b1011101 (
b1011101 ,
#1105
1)
#1110
0)
#1111
b1011110 (
b1011110 ,
#1115
1)
#1120
0)
#1121
b1011111 (
b1011111 ,
#1125
1)
#1130
0)
#1131
b1100000 (
b1100000 ,
#1135
1)
#1140
0)
#1141
b1100001 (
b1100001 ,
#1145
1)
#1150
0)
#1151
b1100010 (
b1100010 ,
#1155
1)
#1160
0)
#1161
b1100011 (
b1100011 ,
#1165
1)
#1170
0)
#1171
b1100100 (
b1100100 ,
#1175
1)
#1180
0)
#1181
b1100101 (
b1100101 ,
#1185
1)
#1190
0)
#1191
b1100110 (
b1100110 ,
#1195
1)
#1200
0)
#1201
b1100111 (
b1100111 ,
#1205
1)
#1210
0)
#1211
b1101000 (
b1101000 ,
#1215
1)
#1220
0)
#1221
b1101001 (
b1101001 ,
#1225
1)
#1230
0)
#1231
b1101010 (
b1101010 ,
#1235
1)
#1240
0)
#1241
b1101011 (
b1101011 ,
#1245
1)
#1250
0)
#1251
b1101100 (
b1101100 ,
#1255
1)
#1260
0)
#1261
b1101101 (
b1101101 ,
#1265
1)
#1270
0)
#1271
b1101110 (
b1101110 ,
#1275
1)
#1280
0)
#1281
b1101111 (
b1101111 ,
#1285
1)
#1290
0)
#1291
b1110000 (
b1110000 ,
#1295
1)
#1300
0)
#1301
b1110001 (
b1110001 ,
#1305
1)
#1310
0)
#1311
b1110010 (
b1110010 ,
#1315
1)
#1320
0)
#1321
b1110011 (
b1110011 ,
#1325
1)
#1330
0)
#1331
b1110100 (
b1110100 ,
#1335
1)
#1340
0)
#1341
b1110101 (
b1110101 ,
#1345
1)
#1350
0)
#1351
b1110110 (
b1110110 ,
#1355
1)
#1360
0)
#1361
b1110111 (
b1110111 ,
#1365
1)
#1370
0)
#1371
b1111000 (
b1111000 ,
#1375
1)
#1380
0)
#1381
b1111001 (
b1111001 ,
#1385
1)
#1390
0)
#1391
b1111010 (
b1111010 ,
#1395
1)
#1400
0)
#1401
b1111011 (
b1111011 ,
#1405
1)
#1410
0)
#1411
b1111100 (
b1111100 ,
#1415
1)
#1420
0)
#1421
b1111101 (
b1111101 ,
#1425
1)
#1430
0)
#1431
b1111110 (
b1111110 ,
#1435
1)
#1440
0)
#1441
b1111111 (
b1111111 ,
#1445
1)
#1450
0)
#1451
b10000000 (
b10000000 ,
#1455
1)
#1460
0)
#1461
b10000001 (
b10000001 ,
#1465
1)
#1470
0)
#1471
b10000010 (
b10000010 ,
#1475
1)
#1480
0)
#1481
b10000011 (
b10000011 ,
#1485
1)
#1490
0)
#1491
b10000100 (
b10000100 ,
#1495
1)
#1500
0)
#1501
b10000101 (
b10000101 ,
#1505
1)
#1510
0)
#1511
b10000110 (
b10000110 ,
#1515
1)
#1520
0)
#1521
b10000111 (
b10000111 ,
#1525
1)
#1530
0)
#1531
b10001000 (
b10001000 ,
#1535
1)
#1540
0)
#1541
b10001001 (
b10001001 ,
#1545
1)
#1550
0)
#1551
b10001010 (
b10001010 ,
#1555
1)
#1560
0)
#1561
b10001011 (
b10001011 ,
#1565
1)
#1570
0)
#1571
b10001100 (
b10001100 ,
#1575
1)
#1580
0)
#1581
b10001101 (
b10001101 ,
#1585
1)
#1590
0)
#1591
b10001110 (
b10001110 ,
#1595
1)
#1600
0)
#1601
b10001111 (
b10001111 ,
#1605
1)
#1610
0)
#1611
b10010000 (
b10010000 ,
#1615
1)
#1620
0)
#1621
b10010001 (
b10010001 ,
#1625
1)
#1630
0)
#1631
b10010010 (
b10010010 ,
#1635
1)
#1640
0)
#1641
b10010011 (
b10010011 ,
#1645
1)
#1650
0)
#1651
b10010100 (
b10010100 ,
#1655
1)
#1660
0)
#1661
b10010101 (
b10010101 ,
#1665
1)
#1670
0)
#1671
b10010110 (
b10010110 ,
#1675
1)
#1680
0)
#1681
b10010111 (
b10010111 ,
#1685
1)
#1690
0)
#1691
b10011000 (
b10011000 ,
#1695
1)
#1700
0)
#1701
b10011001 (
b10011001 ,
#1705
1)
#1710
0)
#1711
b10011010 (
b10011010 ,
#1715
1)
#1720
0)
#1721
b10011011 (
b10011011 ,
#1725
1)
#1730
0)
#1731
b10011100 (
b10011100 ,
#1735
1)
#1740
0)
#1741
b10011101 (
b10011101 ,
#1745
1)
#1750
0)
#1751
b10011110 (
b10011110 ,
#1755
1)
#1760
0)
#1761
b10011111 (
b10011111 ,
#1765
1)
#1770
0)
#1771
b10100000 (
b10100000 ,
#1775
1)
#1780
0)
#1781
b10100001 (
b10100001 ,
#1785
1)
#1790
0)
#1791
b10100010 (
b10100010 ,
#1795
1)
#1800
0)
#1801
b10100011 (
b10100011 ,
#1805
1)
#1810
0)
#1811
b10100100 (
b10100100 ,
#1815
1)
#1820
0)
#1821
b10100101 (
b10100101 ,
#1825
1)
#1830
0)
#1831
b10100110 (
b10100110 ,
#1835
1)
#1840
0)
#1841
b10100111 (
b10100111 ,
#1845
1)
#1850
0)
#1851
b10101000 (
b10101000 ,
#1855
1)
#1860
0)
#1861
b10101001 (
b10101001 ,
#1865
1)
#1870
0)
#1871
b10101010 (
b10101010 ,
#1875
1)
#1880
0)
#1881
b10101011 (
b10101011 ,
#1885
1)
#1890
0)
#1891
b10101100 (
b10101100 ,
#1895
1)
#1900
0)
#1901
b10101101 (
b10101101 ,
#1905
1)
#1910
0)
#1911
b10101110 (
b10101110 ,
#1915
1)
#1920
0)
#1921
b10101111 (
b10101111 ,
#1925
1)
#1930
0)
#1931
b10110000 (
b10110000 ,
#1935
1)
#1940
0)
#1941
b10110001 (
b10110001 ,
#1945
1)
#1950
0)
#1951
b10110010 (
b10110010 ,
#1955
1)
#1960
0)
#1961
b10110011 (
b10110011 ,
#1965
1)
#1970
0)
#1971
b10110100 (
b10110100 ,
#1975
1)
#1980
0)
#1981
b10110101 (
b10110101 ,
#1985
1)
#1990
0)
#1991
b10110110 (
b10110110 ,
#1995
1)
#2000
0)
#2001
b10110111 (
b10110111 ,
#2005
1)
#2010
0)
#2011
b10111000 (
b10111000 ,
#2015
1)
#2020
0)
#2021
b10111001 (
b10111001 ,
#2025
1)
#2030
0)
#2031
b10111010 (
b10111010 ,
#2035
1)
#2040
0)
#2041
b10111011 (
b10111011 ,
#2045
1)
#2050
0)
#2051
b10111100 (
b10111100 ,
#2055
1)
#2060
0)
#2061
b10111101 (
b10111101 ,
#2065
1)
#2070
0)
#2071
b10111110 (
b10111110 ,
#2075
1)
#2080
0)
#2081
b10111111 (
b10111111 ,
#2085
1)
#2090
0)
#2091
b11000000 (
b11000000 ,
#2095
1)
#2100
0)
#2101
b11000001 (
b11000001 ,
#2105
1)
#2110
0)
#2111
b11000010 (
b11000010 ,
#2115
1)
#2120
0)
#2121
b11000011 (
b11000011 ,
#2125
1)
#2130
0)
#2131
b11000100 (
b11000100 ,
#2135
1)
#2140
0)
#2141
b11000101 (
b11000101 ,
#2145
1)
#2150
0)
#2151
b11000110 (
b11000110 ,
#2155
1)
#2160
0)
#2161
b11000111 (
b11000111 ,
#2165
1)
#2170
0)
#2171
b11001000 (
b11001000 ,
#2175
1)
#2180
0)
#2181
b11001001 (
b11001001 ,
#2185
1)
#2190
0)
#2191
b11001010 (
b11001010 ,
#2195
1)
#2200
0)
#2201
b11001011 (
b11001011 ,
#2205
1)
#2210
0)
#2211
b11001100 (
b11001100 ,
#2215
1)
#2220
0)
#2221
b11001101 (
b11001101 ,
#2225
1)
#2230
0)
#2231
b11001110 (
b11001110 ,
#2235
1)
#2240
0)
#2241
b11001111 (
b11001111 ,
#2245
1)
#2250
0)
#2251
b11010000 (
b11010000 ,
#2255
1)
#2260
0)
#2261
b11010001 (
b11010001 ,
#2265
1)
#2270
0)
#2271
b11010010 (
b11010010 ,
#2275
1)
#2280
0)
#2281
b11010011 (
b11010011 ,
#2285
1)
#2290
0)
#2291
b11010100 (
b11010100 ,
#2295
1)
#2300
0)
#2301
b11010101 (
b11010101 ,
#2305
1)
#2310
0)
#2311
b11010110 (
b11010110 ,
#2315
1)
#2320
0)
#2321
b11010111 (
b11010111 ,
#2325
1)
#2330
0)
#2331
b11011000 (
b11011000 ,
#2335
1)
#2340
0)
#2341
b11011001 (
b11011001 ,
#2345
1)
#2350
0)
#2351
b11011010 (
b11011010 ,
#2355
1)
#2360
0)
#2361
b11011011 (
b11011011 ,
#2365
1)
#2370
0)
#2371
b11011100 (
b11011100 ,
#2375
1)
#2380
0)
#2381
b11011101 (
b11011101 ,
#2385
1)
#2390
0)
#2391
b11011110 (
b11011110 ,
#2395
1)
#2400
0)
#2401
b11011111 (
b11011111 ,
#2405
1)
#2410
0)
#2411
b11100000 (
b11100000 ,
#2415
1)
#2420
0)
#2421
b11100001 (
b11100001 ,
#2425
1)
#2430
0)
#2431
b11100010 (
b11100010 ,
#2435
1)
#2440
0)
#2441
b11100011 (
b11100011 ,
#2445
1)
#2450
0)
#2451
b11100100 (
b11100100 ,
#2455
1)
#2460
0)
#2461
b11100101 (
b11100101 ,
#2465
1)
#2470
0)
#2471
b11100110 (
b11100110 ,
#2475
1)
#2480
0)
#2481
b11100111 (
b11100111 ,
#2485
1)
#2490
0)
#2491
b11101000 (
b11101000 ,
#2495
1)
#2500
0)
#2501
b11101001 (
b11101001 ,
#2505
1)
#2510
0)
#2511
b11101010 (
b11101010 ,
#2515
1)
#2520
0)
#2521
b11101011 (
b11101011 ,
#2525
1)
#2530
0)
#2531
b11101100 (
b11101100 ,
#2535
1)
#2540
0)
#2541
b11101101 (
b11101101 ,
#2545
1)
#2550
0)
#2551
b11101110 (
b11101110 ,
#2555
1)
#2560
0)
#2561
b11101111 (
b11101111 ,
#2565
1)
#2570
0)
#2571
b11110000 (
b11110000 ,
#2575
1)
#2580
0)
#2581
b11110001 (
b11110001 ,
#2585
1)
#2590
0)
#2591
b11110010 (
b11110010 ,
#2595
1)
#2600
0)
#2601
b11110011 (
b11110011 ,
#2605
1)
#2610
0)
#2611
b11110100 (
b11110100 ,
#2615
1)
#2620
0)
#2621
b11110101 (
b11110101 ,
#2625
1)
#2630
0)
#2631
b11110110 (
b11110110 ,
#2635
1)
#2640
0)
#2641
b11110111 (
b11110111 ,
#2645
1)
#2650
0)
#2651
b11111000 (
b11111000 ,
#2655
1)
#2660
0)
#2661
b11111001 (
b11111001 ,
#2665
1)
#2670
0)
#2671
b11111010 (
b11111010 ,
#2675
1)
#2680
0)
#2681
b11111011 (
b11111011 ,
#2685
1)
#2690
0)
#2691
b11111100 (
b11111100 ,
#2695
1)
#2700
0)
#2701
b11111101 (
b11111101 ,
#2705
1)
#2710
0)
#2711
b11111110 (
b11111110 ,
#2715
1)
#2720
0)
#2721
b11111111 (
b11111111 ,
#2725
1)
#2730
0)
#2731
b100000000 (
b100000000 ,
#2735
1)
#2740
0)
#2741
b100000001 (
b100000001 ,
#2745
1)
#2750
0)
#2751
b100000010 (
b100000010 ,
#2755
1)
#2760
0)
#2761
b100000011 (
b100000011 ,
#2765
1)
#2770
0)
#2771
b100000100 (
b100000100 ,
#2775
1)
#2780
0)
#2781
b100000101 (
b100000101 ,
#2785
1)
#2790
0)
#2791
b100000110 (
b100000110 ,
#2795
1)
#2800
0)
#2801
b100000111 (
b100000111 ,
#2805
1)
#2810
0)
#2811
b100001000 (
b100001000 ,
#2815
1)
#2820
0)
#2821
b100001001 (
b100001001 ,
#2825
1)
#2830
0)
#2831
b100001010 (
b100001010 ,
#2835
1)
#2840
0)
#2841
b100001011 (
b100001011 ,
#2845
1)
#2850
0)
#2851
b100001100 (
b100001100 ,
#2855
1)
#2860
0)
#2861
b100001101 (
b100001101 ,
#2865
1)
#2870
0)
#2871
b100001110 (
b100001110 ,
#2875
1)
#2880
0)
#2881
b100001111 (
b100001111 ,
#2885
1)
#2890
0)
#2891
b100010000 (
b100010000 ,
#2895
1)
#2900
0)
#2901
b100010001 (
b100010001 ,
#2905
1)
#2910
0)
#2911
b100010010 (
b100010010 ,
#2915
1)
#2920
0)
#2921
b100010011 (
b100010011 ,
#2925
1)
#2930
0)
#2931
b100010100 (
b100010100 ,
#2935
1)
#2940
0)
#2941
b100010101 (
b100010101 ,
#2945
1)
#2950
0)
#2951
b100010110 (
b100010110 ,
#2955
1)
#2960
0)
#2961
b100010111 (
b100010111 ,
#2965
1)
#2970
0)
#2971
b100011000 (
b100011000 ,
#2975
1)
#2980
0)
#2981
b100011001 (
b100011001 ,
#2985
1)
#2990
0)
#2991
b100011010 (
b100011010 ,
#2995
1)
#3000
0)
#3001
b100011011 (
b100011011 ,
#3005
1)
#3010
0)
#3011
b100011100 (
b100011100 ,
#3015
1)
#3020
0)
#3021
b100011101 (
b100011101 ,
#3025
1)
#3030
0)
#3031
b100011110 (
b100011110 ,
#3035
1)
#3040
0)
#3041
b100011111 (
b100011111 ,
#3045
1)
#3050
0)
#3051
b100100000 (
b100100000 ,
#3055
1)
#3060
0)
#3061
b100100001 (
b100100001 ,
#3065
1)
#3070
0)
#3071
b100100010 (
b100100010 ,
#3075
1)
#3080
0)
#3081
b100100011 (
b100100011 ,
#3085
1)
#3090
0)
#3091
b100100100 (
b100100100 ,
#3095
1)
#3100
0)
#3101
b100100101 (
b100100101 ,
#3105
1)
#3110
0)
#3111
b100100110 (
b100100110 ,
#3115
1)
#3120
0)
#3121
b100100111 (
b100100111 ,
#3125
1)
#3130
0)
#3131
b100101000 (
b100101000 ,
#3135
1)
#3140
0)
#3141
b100101001 (
b100101001 ,
#3145
1)
#3150
0)
#3151
b100101010 (
b100101010 ,
#3155
1)
#3160
0)
#3161
b100101011 (
b100101011 ,
#3165
1)
#3170
0)
#3171
b100101100 (
b100101100 ,
#3175
1)
#3180
0)
#3181
b100101101 (
b100101101 ,
#3185
1)
#3190
0)
#3191
b100101110 (
b100101110 ,
#3195
1)
#3200
0)
#3201
b100101111 (
b100101111 ,
#3205
1)
#3210
0)
#3211
b100110000 (
b100110000 ,
#3215
1)
#3220
0)
#3221
b100110001 (
b100110001 ,
#3225
1)
#3230
0)
#3231
b100110010 (
b100110010 ,
#3235
1)
#3240
0)
#3241
b100110011 (
b100110011 ,
#3245
1)
#3250
0)
#3251
b100110100 (
b100110100 ,
#3255
1)
#3260
0)
#3261
b100110101 (
b100110101 ,
#3265
1)
#3270
0)
#3271
b100110110 (
b100110110 ,
#3275
1)
#3280
0)
#3281
b100110111 (
b100110111 ,
#3285
1)
#3290
0)
#3291
b100111000 (
b100111000 ,
#3295
1)
#3300
0)
#3301
b100111001 (
b100111001 ,
#3305
1)
#3310
0)
#3311
b100111010 (
b100111010 ,
#3315
1)
#3320
0)
#3321
b100111011 (
b100111011 ,
#3325
1)
#3330
0)
#3331
b100111100 (
b100111100 ,
#3335
1)
#3340
0)
#3341
b100111101 (
b100111101 ,
#3345
1)
#3350
0)
#3351
b100111110 (
b100111110 ,
#3355
1)
#3360
0)
#3361
b100111111 (
b100111111 ,
#3365
1)
#3370
0)
#3371
b101000000 (
b101000000 ,
#3375
1)
#3380
0)
#3381
b101000001 (
b101000001 ,
#3385
1)
#3390
0)
#3391
b101000010 (
b101000010 ,
#3395
1)
#3400
0)
#3401
b101000011 (
b101000011 ,
#3405
1)
#3410
0)
#3411
b101000100 (
b101000100 ,
#3415
1)
#3420
0)
#3421
b101000101 (
b101000101 ,
#3425
1)
#3430
0)
#3431
b101000110 (
b101000110 ,
#3435
1)
#3440
0)
#3441
b101000111 (
b101000111 ,
#3445
1)
#3450
0)
#3451
b101001000 (
b101001000 ,
#3455
1)
#3460
0)
#3461
b101001001 (
b101001001 ,
#3465
1)
#3470
0)
#3471
b101001010 (
b101001010 ,
#3475
1)
#3480
0)
#3481
b101001011 (
b101001011 ,
#3485
1)
#3490
0)
#3491
b101001100 (
b101001100 ,
#3495
1)
#3500
0)
#3501
b101001101 (
b101001101 ,
#3505
1)
#3510
0)
#3511
b101001110 (
b101001110 ,
#3515
1)
#3520
0)
#3521
b101001111 (
b101001111 ,
#3525
1)
#3530
0)
#3531
b101010000 (
b101010000 ,
#3535
1)
#3540
0)
#3541
b101010001 (
b101010001 ,
#3545
1)
#3550
0)
#3551
b101010010 (
b101010010 ,
#3555
1)
#3560
0)
#3561
b101010011 (
b101010011 ,
#3565
1)
#3570
0)
#3571
b101010100 (
b101010100 ,
#3575
1)
#3580
0)
#3581
b101010101 (
b101010101 ,
#3585
1)
#3590
0)
#3591
b101010110 (
b101010110 ,
#3595
1)
#3600
0)
#3601
b101010111 (
b101010111 ,
#3605
1)
#3610
0)
#3611
b101011000 (
b101011000 ,
#3615
1)
#3620
0)
#3621
b101011001 (
b101011001 ,
#3625
1)
#3630
0)
#3631
b101011010 (
b101011010 ,
#3635
1)
#3640
0)
#3641
b101011011 (
b101011011 ,
#3645
1)
#3650
0)
#3651
b101011100 (
b101011100 ,
#3655
1)
#3660
0)
#3661
b101011101 (
b101011101 ,
#3665
1)
#3670
0)
#3671
b101011110 (
b101011110 ,
#3675
1)
#3680
0)
#3681
b101011111 (
b101011111 ,
#3685
1)
#3690
0)
#3691
b101100000 (
b101100000 ,
#3695
1)
#3700
0)
#3701
b101100001 (
b101100001 ,
#3705
1)
#3710
0)
#3711
b101100010 (
b101100010 ,
#3715
1)
#3720
0)
#3721
b101100011 (
b101100011 ,
#3725
1)
#3730
0)
#3731
b101100100 (
b101100100 ,
#3735
1)
#3740
0)
#3741
b101100101 (
b101100101 ,
#3745
1)
#3750
0)
#3751
b101100110 (
b101100110 ,
#3755
1)
#3760
0)
#3761
b101100111 (
b101100111 ,
#3765
1)
#3770
0)
#3771
b101101000 (
b101101000 ,
#3775
1)
#3780
0)
#3781
b101101001 (
b101101001 ,
#3785
1)
#3790
0)
#3791
b101101010 (
b101101010 ,
#3795
1)
#3800
0)
#3801
b101101011 (
b101101011 ,
#3805
1)
#3810
0)
#3811
b101101100 (
b101101100 ,
#3815
1)
#3820
0)
#3821
b101101101 (
b101101101 ,
#3825
1)
#3830
0)
#3831
b101101110 (
b101101110 ,
#3835
1)
#3840
0)
#3841
b101101111 (
b101101111 ,
#3845
1)
#3850
0)
#3851
b101110000 (
b101110000 ,
#3855
1)
#3860
0)
#3861
b101110001 (
b101110001 ,
#3865
1)
#3870
0)
#3871
b101110010 (
b101110010 ,
#3875
1)
#3880
0)
#3881
b101110011 (
b101110011 ,
#3885
1)
#3890
0)
#3891
b101110100 (
b101110100 ,
#3895
1)
#3900
0)
#3901
b101110101 (
b101110101 ,
#3905
1)
#3910
0)
#3911
b101110110 (
b101110110 ,
#3915
1)
#3920
0)
#3921
b101110111 (
b101110111 ,
#3925
1)
#3930
0)
#3931
b101111000 (
b101111000 ,
#3935
1)
#3940
0)
#3941
b101111001 (
b101111001 ,
#3945
1)
#3950
0)
#3951
b101111010 (
b101111010 ,
#3955
1)
#3960
0)
#3961
b101111011 (
b101111011 ,
#3965
1)
#3970
0)
#3971
b101111100 (
b101111100 ,
#3975
1)
#3980
0)
#3981
b101111101 (
b101111101 ,
#3985
1)
#3990
0)
#3991
b101111110 (
b101111110 ,
#3995
1)
#4000
0)
#4001
b101111111 (
b101111111 ,
#4005
1)
#4010
0)
#4011
b110000000 (
b110000000 ,
#4015
1)
#4020
0)
#4021
b110000001 (
b110000001 ,
#4025
1)
#4030
0)
#4031
b110000010 (
b110000010 ,
#4035
1)
#4040
0)
#4041
b110000011 (
b110000011 ,
#4045
1)
#4050
0)
#4051
b110000100 (
b110000100 ,
#4055
1)
#4060
0)
#4061
b110000101 (
b110000101 ,
#4065
1)
#4070
0)
#4071
b110000110 (
b110000110 ,
#4075
1)
#4080
0)
#4081
b110000111 (
b110000111 ,
#4085
1)
#4090
0)
#4091
b110001000 (
b110001000 ,
#4095
1)
#4100
0)
#4101
b110001001 (
b110001001 ,
#4105
1)
#4110
0)
#4111
b110001010 (
b110001010 ,
#4115
1)
#4120
0)
#4121
b110001011 (
b110001011 ,
#4125
1)
#4130
0)
#4131
b110001100 (
b110001100 ,
#4135
1)
#4140
0)
#4141
b110001101 (
b110001101 ,
#4145
1)
#4150
0)
#4151
b110001110 (
b110001110 ,
#4155
1)
#4160
0)
#4161
b110001111 (
b110001111 ,
#4165
1)
#4170
0)
#4171
b110010000 (
b110010000 ,
#4175
1)
#4180
0)
#4181
b110010001 (
b110010001 ,
#4185
1)
#4190
0)
#4191
b110010010 (
b110010010 ,
#4195
1)
#4200
0)
#4201
b110010011 (
b110010011 ,
#4205
1)
#4210
0)
#4211
b110010100 (
b110010100 ,
#4215
1)
#4220
0)
#4221
b110010101 (
b110010101 ,
#4225
1)
#4230
0)
