contador/count2ms.v
module count2ms(
    count,      // Number of pulses counted
    latch,      // Enabling latching the output
    nreset,     // Resetting the output to 000
    ms          // Output in ms
);

parameter BITS = 4;

// Defining I/O
input [BITS-1 : 0] count;
input latch, nreset;

output [10:0] ms;

// Defining Data Types
wire [BITS-1 : 0] count;
wire latch, nreset;

reg [10:0] ms;

// Code

always @(*) begin
    ms <= count % 1000;
end

endmodule

contador/contadorN.v
`timescale 1ms / 100us

module contadorN(
    NEclk,      // Negative-edge clock
    Nreset,     // Not-reset
    Enable,     // Counting Enabler
    count       // Count output
);

parameter BITS = 4; // Parámetro para el tamaño del contador

// Defining I/O
input NEclk, Nreset, Enable;

output [BITS-1 : 0] count;

// Defining Data Types
wire NEclk, Nreset, Enable;

reg [BITS-1 : 0] count;

// Code
always @ (negedge NEclk or Nreset) begin
    if(Nreset == 1'b0) begin
        count <= 0;
    end
    else begin
        if (Enable == 1'b1) begin
            count <= #1 count + 1;
        end else begin
            count <= #1 count;
        end
    end
end

endmodule

contador/clock.v
`timescale 1ms / 100us
module clock_gen(clk);

parameter PERIOD = 2;

output reg clk;
	 
always
	begin: CLOCK_DRIVER
		clk <= 1'b0;
		#(PERIOD/2);
		clk <= 1'b1;
		#(PERIOD/2);
	end
endmodule

contador/contadorN_tb.v
`include "./contadorN.v"
`include "clock.v"
`include "count2ms.v"

`timescale 1ms / 100us

module count_tb();

parameter size = 10;

wire clk;
clock_gen #(.PERIOD(2)) clk_gen(clk);
reg nr = 0;
reg enable = 0;
reg latch = 0;
wire [size-1:0] count;
wire [10:0] ms;

contadorN #(.BITS(size)) counter (
    .NEclk(clk),
    .Nreset(nr),
    .Enable(enable),
    .count(count)
);

count2ms #(.BITS(size)) millis (
    .count(count),
    .nreset(nr),
    .ms(ms),
    .latch(latch)
);

initial begin
    #1 nr = 1;
    #1 enable = 1;
    #8 nr = 0;
    #4 nr = 1;
    #2 enable = 0;
    #4 enable = 1;
end

initial begin
    #2200 $finish;
end

initial begin
    $dumpfile("counter_test.vcd");
    $dumpvars;
end

initial begin
    $display("\t\tTime\tNreset\tenable\tcount\tms");
    $monitor("%d\t%b\t%b\t%d\t%d",$time,nr,enable,count,ms);
end

endmodule

contador/counter_test.vcd
$date
	Mon Nov 19 16:15:16 2018
$end
$version
	Icarus Verilog
$end
$timescale
	100us
$end
$scope module count_tb $end
$var wire 11 ! ms [10:0] $end
$var wire 10 " count [9:0] $end
$var wire 1 # clk $end
$var reg 1 $ enable $end
$var reg 1 % latch $end
$var reg 1 & nr $end
$scope module clk_gen $end
$var reg 1 # clk $end
$scope begin CLOCK_DRIVER $end
$upscope $end
$upscope $end
$scope module counter $end
$var wire 1 $ Enable $end
$var wire 1 # NEclk $end
$var wire 1 & Nreset $end
$var reg 10 ' count [9:0] $end
$upscope $end
$scope module millis $end
$var wire 10 ( count [9:0] $end
$var wire 1 % latch $end
$var wire 1 & nreset $end
$var reg 11 ) ms [10:0] $end
$upscope $end
$upscope $end
$enddefinitions $end
#0
$dumpvars
b0 )
b0 (
b0 '
0&
0%
0$
0#
b0 "
b0 !
$end
#10
1#
1&
#20
0#
1$
#30
b1 !
b1 )
1#
b1 "
b1 '
b1 (
#40
0#
#50
b10 !
b10 )
1#
b10 "
b10 '
b10 (
#60
0#
#70
b11 !
b11 )
1#
b11 "
b11 '
b11 (
#80
0#
#90
b100 !
b100 )
1#
b100 "
b100 '
b100 (
#100
b0 !
b0 )
b0 "
b0 '
b0 (
0#
0&
#110
1#
#120
0#
#130
1#
#140
0#
1&
#150
b1 !
b1 )
1#
b1 "
b1 '
b1 (
#160
0#
0$
#170
1#
#180
0#
#190
1#
#200
0#
1$
#210
b10 !
b10 )
1#
b10 "
b10 '
b10 (
#220
0#
#230
b11 !
b11 )
1#
b11 "
b11 '
b11 (
#240
0#
#250
b100 !
b100 )
1#
b100 "
b100 '
b100 (
#260
0#
#270
b101 !
b101 )
1#
b101 "
b101 '
b101 (
#280
0#
#290
b110 !
b110 )
1#
b110 "
b110 '
b110 (
#300
0#
#310
b111 !
b111 )
1#
b111 "
b111 '
b111 (
#320
0#
#330
b1000 !
b1000 )
1#
b1000 "
b1000 '
b1000 (
#340
0#
#350
b1001 !
b1001 )
1#
b1001 "
b1001 '
b1001 (
#360
0#
#370
b1010 !
b1010 )
1#
b1010 "
b1010 '
b1010 (
#380
0#
#390
b1011 !
b1011 )
1#
b1011 "
b1011 '
b1011 (
#400
0#
#410
b1100 !
b1100 )
1#
b1100 "
b1100 '
b1100 (
#420
0#
#430
b1101 !
b1101 )
1#
b1101 "
b1101 '
b1101 (
#440
0#
#450
b1110 !
b1110 )
1#
b1110 "
b1110 '
b1110 (
#460
0#
#470
b1111 !
b1111 )
1#
b1111 "
b1111 '
b1111 (
#480
0#
#490
b10000 !
b10000 )
1#
b10000 "
b10000 '
b10000 (
#500
0#
#510
b10001 !
b10001 )
1#
b10001 "
b10001 '
b10001 (
#520
0#
#530
b10010 !
b10010 )
1#
b10010 "
b10010 '
b10010 (
#540
0#
#550
b10011 !
b10011 )
1#
b10011 "
b10011 '
b10011 (
#560
0#
#570
b10100 !
b10100 )
1#
b10100 "
b10100 '
b10100 (
#580
0#
#590
b10101 !
b10101 )
1#
b10101 "
b10101 '
b10101 (
#600
0#
#610
b10110 !
b10110 )
1#
b10110 "
b10110 '
b10110 (
#620
0#
#630
b10111 !
b10111 )
1#
b10111 "
b10111 '
b10111 (
#640
0#
#650
b11000 !
b11000 )
1#
b11000 "
b11000 '
b11000 (
#660
0#
#670
b11001 !
b11001 )
1#
b11001 "
b11001 '
b11001 (
#680
0#
#690
b11010 !
b11010 )
1#
b11010 "
b11010 '
b11010 (
#700
0#
#710
b11011 !
b11011 )
1#
b11011 "
b11011 '
b11011 (
#720
0#
#730
b11100 !
b11100 )
1#
b11100 "
b11100 '
b11100 (
#740
0#
#750
b11101 !
b11101 )
1#
b11101 "
b11101 '
b11101 (
#760
0#
#770
b11110 !
b11110 )
1#
b11110 "
b11110 '
b11110 (
#780
0#
#790
b11111 !
b11111 )
1#
b11111 "
b11111 '
b11111 (
#800
0#
#810
b100000 !
b100000 )
1#
b100000 "
b100000 '
b100000 (
#820
0#
#830
b100001 !
b100001 )
1#
b100001 "
b100001 '
b100001 (
#840
0#
#850
b100010 !
b100010 )
1#
b100010 "
b100010 '
b100010 (
#860
0#
#870
b100011 !
b100011 )
1#
b100011 "
b100011 '
b100011 (
#880
0#
#890
b100100 !
b100100 )
1#
b100100 "
b100100 '
b100100 (
#900
0#
#910
b100101 !
b100101 )
1#
b100101 "
b100101 '
b100101 (
#920
0#
#930
b100110 !
b100110 )
1#
b100110 "
b100110 '
b100110 (
#940
0#
#950
b100111 !
b100111 )
1#
b100111 "
b100111 '
b100111 (
#960
0#
#970
b101000 !
b101000 )
1#
b101000 "
b101000 '
b101000 (
#980
0#
#990
b101001 !
b101001 )
1#
b101001 "
b101001 '
b101001 (
#1000
0#
#1010
b101010 !
b101010 )
1#
b101010 "
b101010 '
b101010 (
#1020
0#
#1030
b101011 !
b101011 )
1#
b101011 "
b101011 '
b101011 (
#1040
0#
#1050
b101100 !
b101100 )
1#
b101100 "
b101100 '
b101100 (
#1060
0#
#1070
b101101 !
b101101 )
1#
b101101 "
b101101 '
b101101 (
#1080
0#
#1090
b101110 !
b101110 )
1#
b101110 "
b101110 '
b101110 (
#1100
0#
#1110
b101111 !
b101111 )
1#
b101111 "
b101111 '
b101111 (
#1120
0#
#1130
b110000 !
b110000 )
1#
b110000 "
b110000 '
b110000 (
#1140
0#
#1150
b110001 !
b110001 )
1#
b110001 "
b110001 '
b110001 (
#1160
0#
#1170
b110010 !
b110010 )
1#
b110010 "
b110010 '
b110010 (
#1180
0#
#1190
b110011 !
b110011 )
1#
b110011 "
b110011 '
b110011 (
#1200
0#
#1210
b110100 !
b110100 )
1#
b110100 "
b110100 '
b110100 (
#1220
0#
#1230
b110101 !
b110101 )
1#
b110101 "
b110101 '
b110101 (
#1240
0#
#1250
b110110 !
b110110 )
1#
b110110 "
b110110 '
b110110 (
#1260
0#
#1270
b110111 !
b110111 )
1#
b110111 "
b110111 '
b110111 (
#1280
0#
#1290
b111000 !
b111000 )
1#
b111000 "
b111000 '
b111000 (
#1300
0#
#1310
b111001 !
b111001 )
1#
b111001 "
b111001 '
b111001 (
#1320
0#
#1330
b111010 !
b111010 )
1#
b111010 "
b111010 '
b111010 (
#1340
0#
#1350
b111011 !
b111011 )
1#
b111011 "
b111011 '
b111011 (
#1360
0#
#1370
b111100 !
b111100 )
1#
b111100 "
b111100 '
b111100 (
#1380
0#
#1390
b111101 !
b111101 )
1#
b111101 "
b111101 '
b111101 (
#1400
0#
#1410
b111110 !
b111110 )
1#
b111110 "
b111110 '
b111110 (
#1420
0#
#1430
b111111 !
b111111 )
1#
b111111 "
b111111 '
b111111 (
#1440
0#
#1450
b1000000 !
b1000000 )
1#
b1000000 "
b1000000 '
b1000000 (
#1460
0#
#1470
b1000001 !
b1000001 )
1#
b1000001 "
b1000001 '
b1000001 (
#1480
0#
#1490
b1000010 !
b1000010 )
1#
b1000010 "
b1000010 '
b1000010 (
#1500
0#
#1510
b1000011 !
b1000011 )
1#
b1000011 "
b1000011 '
b1000011 (
#1520
0#
#1530
b1000100 !
b1000100 )
1#
b1000100 "
b1000100 '
b1000100 (
#1540
0#
#1550
b1000101 !
b1000101 )
1#
b1000101 "
b1000101 '
b1000101 (
#1560
0#
#1570
b1000110 !
b1000110 )
1#
b1000110 "
b1000110 '
b1000110 (
#1580
0#
#1590
b1000111 !
b1000111 )
1#
b1000111 "
b1000111 '
b1000111 (
#1600
0#
#1610
b1001000 !
b1001000 )
1#
b1001000 "
b1001000 '
b1001000 (
#1620
0#
#1630
b1001001 !
b1001001 )
1#
b1001001 "
b1001001 '
b1001001 (
#1640
0#
#1650
b1001010 !
b1001010 )
1#
b1001010 "
b1001010 '
b1001010 (
#1660
0#
#1670
b1001011 !
b1001011 )
1#
b1001011 "
b1001011 '
b1001011 (
#1680
0#
#1690
b1001100 !
b1001100 )
1#
b1001100 "
b1001100 '
b1001100 (
#1700
0#
#1710
b1001101 !
b1001101 )
1#
b1001101 "
b1001101 '
b1001101 (
#1720
0#
#1730
b1001110 !
b1001110 )
1#
b1001110 "
b1001110 '
b1001110 (
#1740
0#
#1750
b1001111 !
b1001111 )
1#
b1001111 "
b1001111 '
b1001111 (
#1760
0#
#1770
b1010000 !
b1010000 )
1#
b1010000 "
b1010000 '
b1010000 (
#1780
0#
#1790
b1010001 !
b1010001 )
1#
b1010001 "
b1010001 '
b1010001 (
#1800
0#
#1810
b1010010 !
b1010010 )
1#
b1010010 "
b1010010 '
b1010010 (
#1820
0#
#1830
b1010011 !
b1010011 )
1#
b1010011 "
b1010011 '
b1010011 (
#1840
0#
#1850
b1010100 !
b1010100 )
1#
b1010100 "
b1010100 '
b1010100 (
#1860
0#
#1870
b1010101 !
b1010101 )
1#
b1010101 "
b1010101 '
b1010101 (
#1880
0#
#1890
b1010110 !
b1010110 )
1#
b1010110 "
b1010110 '
b1010110 (
#1900
0#
#1910
b1010111 !
b1010111 )
1#
b1010111 "
b1010111 '
b1010111 (
#1920
0#
#1930
b1011000 !
b1011000 )
1#
b1011000 "
b1011000 '
b1011000 (
#1940
0#
#1950
b1011001 !
b1011001 )
1#
b1011001 "
b1011001 '
b1011001 (
#1960
0#
#1970
b1011010 !
b1011010 )
1#
b1011010 "
b1011010 '
b1011010 (
#1980
0#
#1990
b1011011 !
b1011011 )
1#
b1011011 "
b1011011 '
b1011011 (
#2000
0#
#2010
b1011100 !
b1011100 )
1#
b1011100 "
b1011100 '
b1011100 (
#2020
0#
#2030
b1011101 !
b1011101 )
1#
b1011101 "
b1011101 '
b1011101 (
#2040
0#
#2050
b1011110 !
b1011110 )
1#
b1011110 "
b1011110 '
b1011110 (
#2060
0#
#2070
b1011111 !
b1011111 )
1#
b1011111 "
b1011111 '
b1011111 (
#2080
0#
#2090
b1100000 !
b1100000 )
1#
b1100000 "
b1100000 '
b1100000 (
#2100
0#
#2110
b1100001 !
b1100001 )
1#
b1100001 "
b1100001 '
b1100001 (
#2120
0#
#2130
b1100010 !
b1100010 )
1#
b1100010 "
b1100010 '
b1100010 (
#2140
0#
#2150
b1100011 !
b1100011 )
1#
b1100011 "
b1100011 '
b1100011 (
#2160
0#
#2170
b1100100 !
b1100100 )
1#
b1100100 "
b1100100 '
b1100100 (
#2180
0#
#2190
b1100101 !
b1100101 )
1#
b1100101 "
b1100101 '
b1100101 (
#2200
0#
#2210
b1100110 !
b1100110 )
1#
b1100110 "
b1100110 '
b1100110 (
#2220
0#
#2230
b1100111 !
b1100111 )
1#
b1100111 "
b1100111 '
b1100111 (
#2240
0#
#2250
b1101000 !
b1101000 )
1#
b1101000 "
b1101000 '
b1101000 (
#2260
0#
#2270
b1101001 !
b1101001 )
1#
b1101001 "
b1101001 '
b1101001 (
#2280
0#
#2290
b1101010 !
b1101010 )
1#
b1101010 "
b1101010 '
b1101010 (
#2300
0#
#2310
b1101011 !
b1101011 )
1#
b1101011 "
b1101011 '
b1101011 (
#2320
0#
#2330
b1101100 !
b1101100 )
1#
b1101100 "
b1101100 '
b1101100 (
#2340
0#
#2350
b1101101 !
b1101101 )
1#
b1101101 "
b1101101 '
b1101101 (
#2360
0#
#2370
b1101110 !
b1101110 )
1#
b1101110 "
b1101110 '
b1101110 (
#2380
0#
#2390
b1101111 !
b1101111 )
1#
b1101111 "
b1101111 '
b1101111 (
#2400
0#
#2410
b1110000 !
b1110000 )
1#
b1110000 "
b1110000 '
b1110000 (
#2420
0#
#2430
b1110001 !
b1110001 )
1#
b1110001 "
b1110001 '
b1110001 (
#2440
0#
#2450
b1110010 !
b1110010 )
1#
b1110010 "
b1110010 '
b1110010 (
#2460
0#
#2470
b1110011 !
b1110011 )
1#
b1110011 "
b1110011 '
b1110011 (
#2480
0#
#2490
b1110100 !
b1110100 )
1#
b1110100 "
b1110100 '
b1110100 (
#2500
0#
#2510
b1110101 !
b1110101 )
1#
b1110101 "
b1110101 '
b1110101 (
#2520
0#
#2530
b1110110 !
b1110110 )
1#
b1110110 "
b1110110 '
b1110110 (
#2540
0#
#2550
b1110111 !
b1110111 )
1#
b1110111 "
b1110111 '
b1110111 (
#2560
0#
#2570
b1111000 !
b1111000 )
1#
b1111000 "
b1111000 '
b1111000 (
#2580
0#
#2590
b1111001 !
b1111001 )
1#
b1111001 "
b1111001 '
b1111001 (
#2600
0#
#2610
b1111010 !
b1111010 )
1#
b1111010 "
b1111010 '
b1111010 (
#2620
0#
#2630
b1111011 !
b1111011 )
1#
b1111011 "
b1111011 '
b1111011 (
#2640
0#
#2650
b1111100 !
b1111100 )
1#
b1111100 "
b1111100 '
b1111100 (
#2660
0#
#2670
b1111101 !
b1111101 )
1#
b1111101 "
b1111101 '
b1111101 (
#2680
0#
#2690
b1111110 !
b1111110 )
1#
b1111110 "
b1111110 '
b1111110 (
#2700
0#
#2710
b1111111 !
b1111111 )
1#
b1111111 "
b1111111 '
b1111111 (
#2720
0#
#2730
b10000000 !
b10000000 )
1#
b10000000 "
b10000000 '
b10000000 (
#2740
0#
#2750
b10000001 !
b10000001 )
1#
b10000001 "
b10000001 '
b10000001 (
#2760
0#
#2770
b10000010 !
b10000010 )
1#
b10000010 "
b10000010 '
b10000010 (
#2780
0#
#2790
b10000011 !
b10000011 )
1#
b10000011 "
b10000011 '
b10000011 (
#2800
0#
#2810
b10000100 !
b10000100 )
1#
b10000100 "
b10000100 '
b10000100 (
#2820
0#
#2830
b10000101 !
b10000101 )
1#
b10000101 "
b10000101 '
b10000101 (
#2840
0#
#2850
b10000110 !
b10000110 )
1#
b10000110 "
b10000110 '
b10000110 (
#2860
0#
#2870
b10000111 !
b10000111 )
1#
b10000111 "
b10000111 '
b10000111 (
#2880
0#
#2890
b10001000 !
b10001000 )
1#
b10001000 "
b10001000 '
b10001000 (
#2900
0#
#2910
b10001001 !
b10001001 )
1#
b10001001 "
b10001001 '
b10001001 (
#2920
0#
#2930
b10001010 !
b10001010 )
1#
b10001010 "
b10001010 '
b10001010 (
#2940
0#
#2950
b10001011 !
b10001011 )
1#
b10001011 "
b10001011 '
b10001011 (
#2960
0#
#2970
b10001100 !
b10001100 )
1#
b10001100 "
b10001100 '
b10001100 (
#2980
0#
#2990
b10001101 !
b10001101 )
1#
b10001101 "
b10001101 '
b10001101 (
#3000
0#
#3010
b10001110 !
b10001110 )
1#
b10001110 "
b10001110 '
b10001110 (
#3020
0#
#3030
b10001111 !
b10001111 )
1#
b10001111 "
b10001111 '
b10001111 (
#3040
0#
#3050
b10010000 !
b10010000 )
1#
b10010000 "
b10010000 '
b10010000 (
#3060
0#
#3070
b10010001 !
b10010001 )
1#
b10010001 "
b10010001 '
b10010001 (
#3080
0#
#3090
b10010010 !
b10010010 )
1#
b10010010 "
b10010010 '
b10010010 (
#3100
0#
#3110
b10010011 !
b10010011 )
1#
b10010011 "
b10010011 '
b10010011 (
#3120
0#
#3130
b10010100 !
b10010100 )
1#
b10010100 "
b10010100 '
b10010100 (
#3140
0#
#3150
b10010101 !
b10010101 )
1#
b10010101 "
b10010101 '
b10010101 (
#3160
0#
#3170
b10010110 !
b10010110 )
1#
b10010110 "
b10010110 '
b10010110 (
#3180
0#
#3190
b10010111 !
b10010111 )
1#
b10010111 "
b10010111 '
b10010111 (
#3200
0#
#3210
b10011000 !
b10011000 )
1#
b10011000 "
b10011000 '
b10011000 (
#3220
0#
#3230
b10011001 !
b10011001 )
1#
b10011001 "
b10011001 '
b10011001 (
#3240
0#
#3250
b10011010 !
b10011010 )
1#
b10011010 "
b10011010 '
b10011010 (
#3260
0#
#3270
b10011011 !
b10011011 )
1#
b10011011 "
b10011011 '
b10011011 (
#3280
0#
#3290
b10011100 !
b10011100 )
1#
b10011100 "
b10011100 '
b10011100 (
#3300
0#
#3310
b10011101 !
b10011101 )
1#
b10011101 "
b10011101 '
b10011101 (
#3320
0#
#3330
b10011110 !
b10011110 )
1#
b10011110 "
b10011110 '
b10011110 (
#3340
0#
#3350
b10011111 !
b10011111 )
1#
b10011111 "
b10011111 '
b10011111 (
#3360
0#
#3370
b10100000 !
b10100000 )
1#
b10100000 "
b10100000 '
b10100000 (
#3380
0#
#3390
b10100001 !
b10100001 )
1#
b10100001 "
b10100001 '
b10100001 (
#3400
0#
#3410
b10100010 !
b10100010 )
1#
b10100010 "
b10100010 '
b10100010 (
#3420
0#
#3430
b10100011 !
b10100011 )
1#
b10100011 "
b10100011 '
b10100011 (
#3440
0#
#3450
b10100100 !
b10100100 )
1#
b10100100 "
b10100100 '
b10100100 (
#3460
0#
#3470
b10100101 !
b10100101 )
1#
b10100101 "
b10100101 '
b10100101 (
#3480
0#
#3490
b10100110 !
b10100110 )
1#
b10100110 "
b10100110 '
b10100110 (
#3500
0#
#3510
b10100111 !
b10100111 )
1#
b10100111 "
b10100111 '
b10100111 (
#3520
0#
#3530
b10101000 !
b10101000 )
1#
b10101000 "
b10101000 '
b10101000 (
#3540
0#
#3550
b10101001 !
b10101001 )
1#
b10101001 "
b10101001 '
b10101001 (
#3560
0#
#3570
b10101010 !
b10101010 )
1#
b10101010 "
b10101010 '
b10101010 (
#3580
0#
#3590
b10101011 !
b10101011 )
1#
b10101011 "
b10101011 '
b10101011 (
#3600
0#
#3610
b10101100 !
b10101100 )
1#
b10101100 "
b10101100 '
b10101100 (
#3620
0#
#3630
b10101101 !
b10101101 )
1#
b10101101 "
b10101101 '
b10101101 (
#3640
0#
#3650
b10101110 !
b10101110 )
1#
b10101110 "
b10101110 '
b10101110 (
#3660
0#
#3670
b10101111 !
b10101111 )
1#
b10101111 "
b10101111 '
b10101111 (
#3680
0#
#3690
b10110000 !
b10110000 )
1#
b10110000 "
b10110000 '
b10110000 (
#3700
0#
#3710
b10110001 !
b10110001 )
1#
b10110001 "
b10110001 '
b10110001 (
#3720
0#
#3730
b10110010 !
b10110010 )
1#
b10110010 "
b10110010 '
b10110010 (
#3740
0#
#3750
b10110011 !
b10110011 )
1#
b10110011 "
b10110011 '
b10110011 (
#3760
0#
#3770
b10110100 !
b10110100 )
1#
b10110100 "
b10110100 '
b10110100 (
#3780
0#
#3790
b10110101 !
b10110101 )
1#
b10110101 "
b10110101 '
b10110101 (
#3800
0#
#3810
b10110110 !
b10110110 )
1#
b10110110 "
b10110110 '
b10110110 (
#3820
0#
#3830
b10110111 !
b10110111 )
1#
b10110111 "
b10110111 '
b10110111 (
#3840
0#
#3850
b10111000 !
b10111000 )
1#
b10111000 "
b10111000 '
b10111000 (
#3860
0#
#3870
b10111001 !
b10111001 )
1#
b10111001 "
b10111001 '
b10111001 (
#3880
0#
#3890
b10111010 !
b10111010 )
1#
b10111010 "
b10111010 '
b10111010 (
#3900
0#
#3910
b10111011 !
b10111011 )
1#
b10111011 "
b10111011 '
b10111011 (
#3920
0#
#3930
b10111100 !
b10111100 )
1#
b10111100 "
b10111100 '
b10111100 (
#3940
0#
#3950
b10111101 !
b10111101 )
1#
b10111101 "
b10111101 '
b10111101 (
#3960
0#
#3970
b10111110 !
b10111110 )
1#
b10111110 "
b10111110 '
b10111110 (
#3980
0#
#3990
b10111111 !
b10111111 )
1#
b10111111 "
b10111111 '
b10111111 (
#4000
0#
#4010
b11000000 !
b11000000 )
1#
b11000000 "
b11000000 '
b11000000 (
#4020
0#
#4030
b11000001 !
b11000001 )
1#
b11000001 "
b11000001 '
b11000001 (
#4040
0#
#4050
b11000010 !
b11000010 )
1#
b11000010 "
b11000010 '
b11000010 (
#4060
0#
#4070
b11000011 !
b11000011 )
1#
b11000011 "
b11000011 '
b11000011 (
#4080
0#
#4090
b11000100 !
b11000100 )
1#
b11000100 "
b11000100 '
b11000100 (
#4100
0#
#4110
b11000101 !
b11000101 )
1#
b11000101 "
b11000101 '
b11000101 (
#4120
0#
#4130
b11000110 !
b11000110 )
1#
b11000110 "
b11000110 '
b11000110 (
#4140
0#
#4150
b11000111 !
b11000111 )
1#
b11000111 "
b11000111 '
b11000111 (
#4160
0#
#4170
b11001000 !
b11001000 )
1#
b11001000 "
b11001000 '
b11001000 (
#4180
0#
#4190
b11001001 !
b11001001 )
1#
b11001001 "
b11001001 '
b11001001 (
#4200
0#
#4210
b11001010 !
b11001010 )
1#
b11001010 "
b11001010 '
b11001010 (
#4220
0#
#4230
b11001011 !
b11001011 )
1#
b11001011 "
b11001011 '
b11001011 (
#4240
0#
#4250
b11001100 !
b11001100 )
1#
b11001100 "
b11001100 '
b11001100 (
#4260
0#
#4270
b11001101 !
b11001101 )
1#
b11001101 "
b11001101 '
b11001101 (
#4280
0#
#4290
b11001110 !
b11001110 )
1#
b11001110 "
b11001110 '
b11001110 (
#4300
0#
#4310
b11001111 !
b11001111 )
1#
b11001111 "
b11001111 '
b11001111 (
#4320
0#
#4330
b11010000 !
b11010000 )
1#
b11010000 "
b11010000 '
b11010000 (
#4340
0#
#4350
b11010001 !
b11010001 )
1#
b11010001 "
b11010001 '
b11010001 (
#4360
0#
#4370
b11010010 !
b11010010 )
1#
b11010010 "
b11010010 '
b11010010 (
#4380
0#
#4390
b11010011 !
b11010011 )
1#
b11010011 "
b11010011 '
b11010011 (
#4400
0#
#4410
b11010100 !
b11010100 )
1#
b11010100 "
b11010100 '
b11010100 (
#4420
0#
#4430
b11010101 !
b11010101 )
1#
b11010101 "
b11010101 '
b11010101 (
#4440
0#
#4450
b11010110 !
b11010110 )
1#
b11010110 "
b11010110 '
b11010110 (
#4460
0#
#4470
b11010111 !
b11010111 )
1#
b11010111 "
b11010111 '
b11010111 (
#4480
0#
#4490
b11011000 !
b11011000 )
1#
b11011000 "
b11011000 '
b11011000 (
#4500
0#
#4510
b11011001 !
b11011001 )
1#
b11011001 "
b11011001 '
b11011001 (
#4520
0#
#4530
b11011010 !
b11011010 )
1#
b11011010 "
b11011010 '
b11011010 (
#4540
0#
#4550
b11011011 !
b11011011 )
1#
b11011011 "
b11011011 '
b11011011 (
#4560
0#
#4570
b11011100 !
b11011100 )
1#
b11011100 "
b11011100 '
b11011100 (
#4580
0#
#4590
b11011101 !
b11011101 )
1#
b11011101 "
b11011101 '
b11011101 (
#4600
0#
#4610
b11011110 !
b11011110 )
1#
b11011110 "
b11011110 '
b11011110 (
#4620
0#
#4630
b11011111 !
b11011111 )
1#
b11011111 "
b11011111 '
b11011111 (
#4640
0#
#4650
b11100000 !
b11100000 )
1#
b11100000 "
b11100000 '
b11100000 (
#4660
0#
#4670
b11100001 !
b11100001 )
1#
b11100001 "
b11100001 '
b11100001 (
#4680
0#
#4690
b11100010 !
b11100010 )
1#
b11100010 "
b11100010 '
b11100010 (
#4700
0#
#4710
b11100011 !
b11100011 )
1#
b11100011 "
b11100011 '
b11100011 (
#4720
0#
#4730
b11100100 !
b11100100 )
1#
b11100100 "
b11100100 '
b11100100 (
#4740
0#
#4750
b11100101 !
b11100101 )
1#
b11100101 "
b11100101 '
b11100101 (
#4760
0#
#4770
b11100110 !
b11100110 )
1#
b11100110 "
b11100110 '
b11100110 (
#4780
0#
#4790
b11100111 !
b11100111 )
1#
b11100111 "
b11100111 '
b11100111 (
#4800
0#
#4810
b11101000 !
b11101000 )
1#
b11101000 "
b11101000 '
b11101000 (
#4820
0#
#4830
b11101001 !
b11101001 )
1#
b11101001 "
b11101001 '
b11101001 (
#4840
0#
#4850
b11101010 !
b11101010 )
1#
b11101010 "
b11101010 '
b11101010 (
#4860
0#
#4870
b11101011 !
b11101011 )
1#
b11101011 "
b11101011 '
b11101011 (
#4880
0#
#4890
b11101100 !
b11101100 )
1#
b11101100 "
b11101100 '
b11101100 (
#4900
0#
#4910
b11101101 !
b11101101 )
1#
b11101101 "
b11101101 '
b11101101 (
#4920
0#
#4930
b11101110 !
b11101110 )
1#
b11101110 "
b11101110 '
b11101110 (
#4940
0#
#4950
b11101111 !
b11101111 )
1#
b11101111 "
b11101111 '
b11101111 (
#4960
0#
#4970
b11110000 !
b11110000 )
1#
b11110000 "
b11110000 '
b11110000 (
#4980
0#
#4990
b11110001 !
b11110001 )
1#
b11110001 "
b11110001 '
b11110001 (
#5000
0#
#5010
b11110010 !
b11110010 )
1#
b11110010 "
b11110010 '
b11110010 (
#5020
0#
#5030
b11110011 !
b11110011 )
1#
b11110011 "
b11110011 '
b11110011 (
#5040
0#
#5050
b11110100 !
b11110100 )
1#
b11110100 "
b11110100 '
b11110100 (
#5060
0#
#5070
b11110101 !
b11110101 )
1#
b11110101 "
b11110101 '
b11110101 (
#5080
0#
#5090
b11110110 !
b11110110 )
1#
b11110110 "
b11110110 '
b11110110 (
#5100
0#
#5110
b11110111 !
b11110111 )
1#
b11110111 "
b11110111 '
b11110111 (
#5120
0#
#5130
b11111000 !
b11111000 )
1#
b11111000 "
b11111000 '
b11111000 (
#5140
0#
#5150
b11111001 !
b11111001 )
1#
b11111001 "
b11111001 '
b11111001 (
#5160
0#
#5170
b11111010 !
b11111010 )
1#
b11111010 "
b11111010 '
b11111010 (
#5180
0#
#5190
b11111011 !
b11111011 )
1#
b11111011 "
b11111011 '
b11111011 (
#5200
0#
#5210
b11111100 !
b11111100 )
1#
b11111100 "
b11111100 '
b11111100 (
#5220
0#
#5230
b11111101 !
b11111101 )
1#
b11111101 "
b11111101 '
b11111101 (
#5240
0#
#5250
b11111110 !
b11111110 )
1#
b11111110 "
b11111110 '
b11111110 (
#5260
0#
#5270
b11111111 !
b11111111 )
1#
b11111111 "
b11111111 '
b11111111 (
#5280
0#
#5290
b100000000 !
b100000000 )
1#
b100000000 "
b100000000 '
b100000000 (
#5300
0#
#5310
b100000001 !
b100000001 )
1#
b100000001 "
b100000001 '
b100000001 (
#5320
0#
#5330
b100000010 !
b100000010 )
1#
b100000010 "
b100000010 '
b100000010 (
#5340
0#
#5350
b100000011 !
b100000011 )
1#
b100000011 "
b100000011 '
b100000011 (
#5360
0#
#5370
b100000100 !
b100000100 )
1#
b100000100 "
b100000100 '
b100000100 (
#5380
0#
#5390
b100000101 !
b100000101 )
1#
b100000101 "
b100000101 '
b100000101 (
#5400
0#
#5410
b100000110 !
b100000110 )
1#
b100000110 "
b100000110 '
b100000110 (
#5420
0#
#5430
b100000111 !
b100000111 )
1#
b100000111 "
b100000111 '
b100000111 (
#5440
0#
#5450
b100001000 !
b100001000 )
1#
b100001000 "
b100001000 '
b100001000 (
#5460
0#
#5470
b100001001 !
b100001001 )
1#
b100001001 "
b100001001 '
b100001001 (
#5480
0#
#5490
b100001010 !
b100001010 )
1#
b100001010 "
b100001010 '
b100001010 (
#5500
0#
#5510
b100001011 !
b100001011 )
1#
b100001011 "
b100001011 '
b100001011 (
#5520
0#
#5530
b100001100 !
b100001100 )
1#
b100001100 "
b100001100 '
b100001100 (
#5540
0#
#5550
b100001101 !
b100001101 )
1#
b100001101 "
b100001101 '
b100001101 (
#5560
0#
#5570
b100001110 !
b100001110 )
1#
b100001110 "
b100001110 '
b100001110 (
#5580
0#
#5590
b100001111 !
b100001111 )
1#
b100001111 "
b100001111 '
b100001111 (
#5600
0#
#5610
b100010000 !
b100010000 )
1#
b100010000 "
b100010000 '
b100010000 (
#5620
0#
#5630
b100010001 !
b100010001 )
1#
b100010001 "
b100010001 '
b100010001 (
#5640
0#
#5650
b100010010 !
b100010010 )
1#
b100010010 "
b100010010 '
b100010010 (
#5660
0#
#5670
b100010011 !
b100010011 )
1#
b100010011 "
b100010011 '
b100010011 (
#5680
0#
#5690
b100010100 !
b100010100 )
1#
b100010100 "
b100010100 '
b100010100 (
#5700
0#
#5710
b100010101 !
b100010101 )
1#
b100010101 "
b100010101 '
b100010101 (
#5720
0#
