contador/contadorN.v
`timescale 1ms / 100us

module contadorN(
    NEclk,      // Negative-edge clock
    Nreset,     // Not-reset
    Enable,     // Counting Enabler
    count       // Count output
);

parameter BITS = 4; // Parámetro para el tamaño del contador

// Defining I/O
input NEclk, Nreset, Enable;

output [BITS-1 : 0] count;

// Defining Data Types
wire NEclk, Nreset, Enable;

reg [BITS-1 : 0] count;

// Code
always @ (negedge NEclk or Nreset) begin
    if(Nreset == 1'b0) begin
        count <= 0;
    end
    else begin
        if (Enable == 1'b1) begin
            count <= #1 count + 1;
        end else begin
            count <= #1 count;
        end
    end
end

endmodule

contador/clock.v
`timescale 1ms / 100us
module clock_gen(clk);

parameter PERIOD = 2;

output reg clk;
	 
always
	begin: CLOCK_DRIVER
		clk <= 1'b0;
		#(PERIOD/2);
		clk <= 1'b1;
		#(PERIOD/2);
	end
endmodule

contador/contadorN_tb.v
`include "./contadorN.v"
`include "clock.v"
`timescale 1ms / 100us

module count_tb();

parameter size = 8;

wire clk;
clock_gen #(.PERIOD(6)) clk_gen(clk);
reg nr = 0;
reg enable = 0;
wire [size-1:0] count;

contadorN #(.BITS(size)) counter (
    .NEclk(clk),
    .Nreset(nr),
    .Enable(enable),
    .count(count)
);

initial begin
    #1 nr = 1;
    #1 enable = 1;
    #8 nr = 0;
    #4 nr = 1;
    #2 enable = 0;
    #4 enable = 1;
end

initial begin
    #40 $finish;
end

initial begin
    $dumpfile("counter_test.vcd");
    $dumpvars;
end

initial begin
    $display("\t\tTime\tClk\tNreset\tenable\tcount");
    $monitor("%d\t%b\t%b\t%b\t%d",$time,clk,nr,enable,count);
end

endmodule

contador/counter_test.vcd
$date
	Mon Nov 19 15:08:15 2018
$end
$version
	Icarus Verilog
$end
$timescale
	100us
$end
$scope module count_tb $end
$var wire 8 ! count [7:0] $end
$var wire 1 " clk $end
$var reg 1 # enable $end
$var reg 1 $ nr $end
$scope module clk_gen $end
$var reg 1 " clk $end
$scope begin CLOCK_DRIVER $end
$upscope $end
$upscope $end
$scope module counter $end
$var wire 1 # Enable $end
$var wire 1 " NEclk $end
$var wire 1 $ Nreset $end
$var reg 8 % count [7:0] $end
$upscope $end
$upscope $end
$enddefinitions $end
#0
$dumpvars
b0 %
0$
0#
0"
b0 !
$end
#10
1$
#20
1#
#30
1"
#60
0"
#70
b1 !
b1 %
#90
1"
#100
b0 !
b0 %
0$
#120
0"
#140
1$
#150
1"
b1 !
b1 %
#160
0#
#180
0"
#200
1#
#210
1"
#240
0"
#250
b10 !
b10 %
#270
1"
#300
0"
#310
b11 !
b11 %
#330
1"
#360
0"
#370
b100 !
b100 %
