contador/count2watch.v
module count2watch(
    count,      // Number of pulses counted
    nreset,     // Resetting the output to 000
    ms,         // Output in ms
    s,          // Output in s
    min,        // Output in min
    hr          // Output in hr
);

parameter BITS = 4;

// Defining I/O
input [BITS-1 : 0] count;
input latch, nreset;

output [9:0] ms;
output [5:0] s;
output [5:0] min;
output [3:0] hr;

// Defining Data Types
wire [BITS-1 : 0] count;
wire latch, nreset;

reg [9:0] ms;
reg [5:0] s;
reg [5:0] min;
reg [3:0] hr;

// Code

always @(*) begin
    ms <= count % 1000;
    s <= (count/1000) % 60;
    min <= (count/1000/60) % 60;
    hr <= (count/1000/60/60) % 10;
end

endmodule

contador/watch_tb.v
`include "count2watch.v"

`timescale 100us / 100us

module watch_tb();

parameter size = 26;


// Testable Variables
reg nr = 0;
reg enable = 0;
reg [size-1:0] count;


// Test Outputs
wire [9:0] ms;
wire [5:0] s;
wire [5:0] min;
wire [3:0] hr;

count2watch #(.BITS(size)) watch_data (
    .count(count),
    .nreset(nr),
    .ms(ms),
    .s(s),
    .min(min),
    .hr(hr)
);

initial begin
    #10 nr = 1;
    #10 enable = 1;
    #80 nr = 0;
    #40 nr = 1;
    #20 enable = 0;
    #40 enable = 1;
end

initial begin
    #10 count = 1100;       // 1s 100ms
    #10 count = 7200000;    // 2h 0m 0s 0ms
    #10 count = 123548;     // 0h 2m 3s 548ms
end

initial begin
    #100000 $finish;
end

initial begin
    $dumpfile("watch_test.vcd");
    $dumpvars;
end

initial begin
    $display("\t\tTime\tcount\t\tOutput");
    $monitor("%d\t%d\t%d:%d:%d:(%d)",$time,count,hr,min,s,ms);
end

endmodule

contador/watch_test.vcd
$date
	Mon Nov 19 19:33:49 2018
$end
$version
	Icarus Verilog
$end
$timescale
	100us
$end
$scope module watch_tb $end
$var wire 6 ! s [5:0] $end
$var wire 10 " ms [9:0] $end
$var wire 6 # min [5:0] $end
$var wire 4 $ hr [3:0] $end
$var reg 26 % count [25:0] $end
$var reg 1 & enable $end
$var reg 1 ' nr $end
$scope module watch_data $end
$var wire 26 ( count [25:0] $end
$var wire 1 ) latch $end
$var wire 1 ' nreset $end
$var reg 4 * hr [3:0] $end
$var reg 6 + min [5:0] $end
$var reg 10 , ms [9:0] $end
$var reg 6 - s [5:0] $end
$upscope $end
$upscope $end
$enddefinitions $end
#0
$dumpvars
bx -
bx ,
bx +
bx *
z)
bx (
0'
0&
bx %
bx $
bx #
bx "
bx !
$end
#10
b0 $
b0 *
b0 #
b0 +
b1 !
b1 -
b1100100 "
b1100100 ,
b10001001100 %
b10001001100 (
1'
#20
b10 $
b10 *
b0 !
b0 -
b0 "
b0 ,
b11011011101110100000000 %
b11011011101110100000000 (
1&
#30
b0 $
b0 *
b10 #
b10 +
b11 !
b11 -
b1000100100 "
b1000100100 ,
b11110001010011100 %
b11110001010011100 (
#100
0'
#140
1'
#160
0&
#200
1&
